drugdetector/__init__.py
drugdetector/detect.py
drugdetector/utils.py
drugdetector-0.3.3.dist-info/METADATA
drugdetector-0.3.3.dist-info/WHEEL
drugdetector-0.3.3.dist-info/top_level.txt
drugdetector-0.3.3.dist-info/RECORD
