Metadata-Version: 2.1
Name: drugdetector
Version: 0.3.3
Summary: A simple wrapper to support drug detection in medical texts.
Home-page: https://github.com/fabriceyhc/drugdetector
Author: Fabrice Harel-Canada
Author-email: fabricehc@cs.ucla.edu
Classifier: Programming Language :: Python :: 3
Classifier: License :: OSI Approved :: MIT License
Classifier: Operating System :: OS Independent
Requires-Python: >=3.10
Requires-Dist: accelerate
Requires-Dist: guidance
Requires-Dist: llama-cpp-python
Requires-Dist: transformers
Requires-Dist: optimum
